MANIFEST.in
README.md
rmb.py
setup.cfg
setup.py
rmb.egg-info/PKG-INFO
rmb.egg-info/SOURCES.txt
rmb.egg-info/dependency_links.txt
rmb.egg-info/requires.txt
rmb.egg-info/top_level.txt