Metadata-Version: 1.1
Name: rmb
Version: 0.0.3
Summary: rmb is a Python RMB translation library
Home-page: http://github.com/likang/python-rmb
Author: Kang Li
Author-email: eastern.fence@gmail.com
License: MIT
Download-URL: http://pypi.python.org/pypi/rmb
Platform: any
